yemot_speech/__init__.py
yemot_speech/base.py
yemot_speech/stt.py
yemot_speech/tts.py
yemot_speech/providors/amazon.py
yemot_speech/providors/amazon_tts.py
yemot_speech/providors/azure_tts.py
yemot_speech/providors/google.py
yemot_speech/providors/gtts.py
yemot_speech/providors/local.py
yemot_speech/providors/openai.py
yemot_speech/providors/openai_tts.py
yemot_speech-0.1.5.dist-info/METADATA
yemot_speech-0.1.5.dist-info/WHEEL
yemot_speech-0.1.5.dist-info/entry_points.txt
yemot_speech-0.1.5.dist-info/RECORD
