Metadata-Version: 2.4
Name: yemot-speech
Version: 0.1.5
Summary: Speech-to-Text and Text-to-Speech library for Yemot HaMashiach systems
Project-URL: Homepage, https://github.com/your-username/yemot-speech
Project-URL: Repository, https://github.com/your-username/yemot-speech
Project-URL: Issues, https://github.com/your-username/yemot-speech/issues
Author-email: davidTheDeveloper <dev@code-chai.com>
Keywords: audio,hebrew,speech,stt,transcription,tts,yemot
Classifier: Development Status :: 3 - Alpha
Classifier: Intended Audience :: Developers
Classifier: License :: OSI Approved :: MIT License
Classifier: Operating System :: OS Independent
Classifier: Programming Language :: Python :: 3
Classifier: Programming Language :: Python :: 3.8
Classifier: Programming Language :: Python :: 3.9
Classifier: Programming Language :: Python :: 3.10
Classifier: Programming Language :: Python :: 3.11
Classifier: Programming Language :: Python :: 3.12
Classifier: Topic :: Multimedia :: Sound/Audio :: Speech
Classifier: Topic :: Software Development :: Libraries :: Python Modules
Requires-Python: >=3.8
Provides-Extra: all
Requires-Dist: azure-cognitiveservices-speech>=1.24.0; extra == 'all'
Requires-Dist: boto3>=1.26.0; extra == 'all'
Requires-Dist: google-cloud-speech>=2.0.0; extra == 'all'
Requires-Dist: gtts>=2.3.0; extra == 'all'
Requires-Dist: openai-whisper>=20230314; extra == 'all'
Requires-Dist: openai>=1.0.0; extra == 'all'
Requires-Dist: pygame>=2.0.0; extra == 'all'
Requires-Dist: speechrecognition>=3.10.0; extra == 'all'
Provides-Extra: amazon
Requires-Dist: boto3>=1.26.0; extra == 'amazon'
Provides-Extra: azure
Requires-Dist: azure-cognitiveservices-speech>=1.24.0; extra == 'azure'
Provides-Extra: dev
Requires-Dist: black>=22.0.0; extra == 'dev'
Requires-Dist: build>=0.8.0; extra == 'dev'
Requires-Dist: flake8>=5.0.0; extra == 'dev'
Requires-Dist: isort>=5.0.0; extra == 'dev'
Requires-Dist: mypy>=1.0.0; extra == 'dev'
Requires-Dist: pytest-cov>=4.0.0; extra == 'dev'
Requires-Dist: pytest>=7.0.0; extra == 'dev'
Requires-Dist: twine>=4.0.0; extra == 'dev'
Provides-Extra: google
Requires-Dist: google-cloud-speech>=2.0.0; extra == 'google'
Provides-Extra: local
Requires-Dist: openai-whisper>=20230314; extra == 'local'
Requires-Dist: speechrecognition>=3.10.0; extra == 'local'
Provides-Extra: openai
Requires-Dist: openai>=1.0.0; extra == 'openai'
Provides-Extra: tts
Requires-Dist: gtts>=2.3.0; extra == 'tts'
Requires-Dist: pygame>=2.0.0; extra == 'tts'
Provides-Extra: tts-amazon
Requires-Dist: boto3>=1.26.0; extra == 'tts-amazon'
Provides-Extra: tts-azure
Requires-Dist: azure-cognitiveservices-speech>=1.24.0; extra == 'tts-azure'
Provides-Extra: tts-openai
Requires-Dist: openai>=1.0.0; extra == 'tts-openai'
